Workbook

Sheet COA
A1: AcctCode | B1: AcctName | C1: Levels | D1: Postable | E1: FatherNum | F1: U_TypeProduct | G1: U_Channel | H1: U_ForeignName
A2: 1 | B2: ບັນຊີ ປະເພດ 1 – ບັນ​ດາ ບັນຊີ ຊັບ​ສິນ​ໝູນ​ວຽນ | C2: 2 | D2: N | E2: 100000000000000 | F2: ? | G2: ? | H2: CLASS 1 – CURRENT ASSETS
A3: 10 | B3: ເງິນສົດໃນ​ຄັງ, ເງິນ​ຍ່ອຍ, ເງິນຝາກທະນາຄານ, ສະ​ຖາ​ບັນ​ການ​ເງິນ, ເງິນ​ຝາກ​ຄັງ​ເງິນ​ແຫ່ງ​ຊາດ," | C3: 3 | D3: N | E3: 1 | F3: ? | G3: ? | H3: Cash on Hand, Petty Cash, Cash in Banks, Financial Institutions and National Treasury
A4: 101 | B4: ​ເງິນສົດ​ໃນ​ຄັງ | C4: 4 | D4: N | E4: 10 | F4: ? | G4: ? | H4: ​Cash on Hand
A5: 1011 | B5: ​ເງິນສົດ​ເປັນ​ເງິນກີບ | C5: 5 | D5: N | E5: 101 | F5: ? | G5: ? | H5: Cash on hand – Kip
A6: 1011.01 | B6: ເງິນສົດຄັງຍ່ອຍ | C6: 6 | D6: N | E6: 1011 | F6: ? | G6: ? | H6: Cash of Sub Branch
A7: 1011.001 | B7: ເງິນສົດຄັງຍ່ອຍ | C7: 7 | D7: N | E7: 1011.01 | F7: ? | G7: ? | H7: Cash of Sub Branch
A8: 1011.01.00 | B8: ເງິນສົດຍ່ອຍ - ກີບ | C8: 8 | D8: Y | E8: 1011.001 | F8: ? | G8: ? | H8: Cash on hand - LAK
A9: 1011.01.01 | B9: ເງິນສົດຍ່ອຍ - ໂດລາ | C9: 8 | D9: Y | E9: 1011.001 | F9: ? | G9: ? | H9: Cash on hand - USD
A10: 1011.01.02 | B10: ເງິນສົດຍ່ອຍ - ບາດ | C10: 8 | D10: Y | E10: 1011.001 | F10: ? | G10: ? | H10: Cash on hand - THB
A11: 1011.01.03 | B11: ເງິນສົດຍ່ອຍ - ອື່ນໆ | C11: 8 | D11: Y | E11: 1011.001 | F11: ? | G11: ? | H11: Cash on hand – Other
A12: 1012 | B12: ເງິນສົດ​ເປັນ​ເງິນ​ຕາ​ຕ່າງ​ປະ​ເທດ | C12: 5 | D12: N | E12: 101 | F12: ? | G12: ? | H12: Cash on hand – Foreign currencies
A13: 1013 | B13: ເງິນ​ສົດ​ຍ່ອຍ | C13: 5 | D13: N | E13: 101 | F13: ? | G13: ? | H13: Petty cash
A14: 1013 | B14: ເງິນ​ສົດ​ຍ່ອຍ | C14: 6 | D14: N | E14: 1013 | F14: ? | G14: ? | H14: Petty cash
A15: 1013 | B15: ເງິນສົດໃນມື - ກີບ | C15: 7 | D15: N | E15: 1013.0 | F15: ? | G15: ? | H15: Petty cash - LAK
A16: 1013.001 | B16: ເງິນສົດໃນມື - ກີບ | C16: 8 | D16: Y | E16: 1013.00 | F16: ? | G16: ? | H16: Petty cash - LAK
A17: 1013.01 | B17: ເງິນສົດໃນມື - ໂດລາ | C17: 8 | D17: Y | E17: 1013.00 | F17: ? | G17: ? | H17: Petty Cash - USD
A18: 1013.02 | B18: ເງິນສົດໃນມື - ບາດ | C18: 8 | D18: Y | E18: 1013.00 | F18: ? | G18: ? | H18: Petty Cash - THB
A19: 1013.03 | B19: ເງິນສົດໃນມື - ອື່ນໆ | C19: 8 | D19: Y | E19: 1013.00 | F19: ? | G19: ? | H19: Petty Cash - Other
A20: 1014 | B20: ເງິນສົດກຳລັງນຳຝາກ - ທະນາຄານບໍ່ທັນໄດ້ຈົດເຂົ້າບັນຊີ | C20: 5 | D20: N | E20: 101 | F20: ? | G20: ? | H20: Cash in transit – not yet recorded in banks’ accounting
A21: 1017 | B21: ລ່ວງໜ້າ​ເງິນ​ສົດ | C21: 5 | D21: N | E21: 101 | F21: ? | G21: ? | H21: Cash advance
A22: 1017.01 | B22: ເງິນເບີກລ່ວງໜ້າ | C22: 6 | D22: N | E22: 1017 | F22: ? | G22: ? | H22: Advances
A23: 1017.02 | B23: ແບ່ງສ່ວນຈ່າຍອາກອນລາຍໄດ້ຫັກຕອນທີ່ຈ່າຍ | C23: 6 | D23: N | E23: 1017 | F23: ? | G23: ? | H23: Prepaid Withholding Tax
A24: 1017.03 | B24: ເງິນມັດຈຳ | C24: 6 | D24: N | E24: 1017 | F24: ? | G24: ? | H24: Deposits
A25: 1017.003 | B25: ເງິນມັດຈຳ | C25: 7 | D25: N | E25: 1017.03 | F25: ? | G25: ? | H25: Deposits
A26: 1017.03.01 | B26: ເງິນມັດຈຳ ບັດນໍ້າມັນ | C26: 8 | D26: Y | E26: 1017.003 | F26: ? | G26: ? | H26: Deposits Plus Card
A27: 1017.04 | B27: ແຊັກສັ່ງຈ່າຍລ່ວງໜ້າ | C27: 6 | D27: N | E27: 1017 | F27: ? | G27: ? | H27: Post Dated Cheque
A28: 1017.05 | B28: ຈ່າຍລ່ວງໜ້າ (ມັດຈຳ) | C28: 6 | D28: N | E28: 1017 | F28: ? | G28: ? | H28: Prepayment
A29: 1017.06 | B29: ຈ່າຍລ່ວງໜ້າ | C29: 6 | D29: N | E29: 1017 | F29: ? | G29: ? | H29: Prepaid - Expense
A30: 1017.07 | B30: ຈ່າຍລ່ວງໜ້າ - ຜົນຕອບແທນໃຫ້ຕົວແທນ | C30: 6 | D30: N | E30: 1017 | F30: ? | G30: ? | H30: Prepayment - Commission Due to Agent
A31: 1017.08 | B31: ໜີ້ຕ້ອງສົ່ງ ອາກອນສົ້ນເຂົ້າ ປະກັນໄພຕໍ່ | C31: 6 | D31: N | E31: 1017 | F31: ? | G31: ? | H31: Value Added Tax - Input Tax for Reinsurance Ceed
A32: 1017.09 | B32: ສ່ວນຫຼຸດໃນການຊື້ ອື່ນໆ | C32: 6 | D32: N | E32: 1017 | F32: ? | G32: ? | H32: Purchase rebates, discounts, allowances
A33: 1017.10 | B33: ອາກອນມູນຄ່າເພີ່ມລາຍຈ່າຍ | C33: 6 | D33: N | E33: 1017 | F33: ? | G33: ? | H33: Value added taxies. Expenditure 07%
A34: 1017.11 | B34: ອາກອນມູນຄ່າເພີ່ມຫັກໃນເດືອນກ່ອນຍັງບໍ່ໝົດ | C34: 6 | D34: N | E34: 1017 | F34: ? | G34: ? | H34: Value added taies that was not fully deducted from the previous months
A35: 1017.12 | B35: ໜ້າຕ້ອງຮັບ MSITB | C35: 6 | D35: N | E35: 1017 | F35: ? | G35: ? | H35: Account Receivable for MSITB
A36: 1017.13 | B36: ໜີ້ຕ້ອງຮັບ ເງິນຝາກຄໍ້າປະກັນ | C36: 6 | D36: N | E36: 1017 | F36: ? | G36: ? | H36: Account receivable for Security Deposit to Bank
A37: 102 | B37: ເງິນຝາກທະນາຄານ, ສະຖາບັນການເງິນ ແລະ ສະ​ຖາ​ບັນ​ທີ່​ຄ້າຍ​ຄື​ກັນ" | C37: 4 | D37: N | E37: 10 | F37: ? | G37: ? | H37: Banks, Financial and Similar Institutions
A38: 1021 | B38: ເງິນຝາກທະນາຄານເປັນ​ເງິນ​ກີບ | C38: 5 | D38: N | E38: 102 | F38: ? | G38: ? | H38: Bank accounts in Kip
A39: 1021.01 | B39: ເງິນຝາກທະນາຄານບັນຊີກະແສລາຍວັນ | C39: 6 | D39: N | E39: 1021 | F39: ? | G39: ? | H39: Cash at Banks - Current Accounts
A40: 1021.001 | B40: ເງິນຝາກທະນາຄານບັນຊີກະແສລາຍວັນ | C40: 7 | D40: N | E40: 1021.01 | F40: ? | G40: ? | H40: Cash at Banks - Current Accounts
A41: 1021.01.01 | B41: ເງິນຝາກກະແສລາຍວັນ - BCEL - MSIG SOKXAY - 010-13-00011-201 - LAK | C41: 8 | D41: Y | E41: 1021.001 | F41: ? | G41: ? | H41: Current Accounts - BCEL - MSIG SOKXAY - 010-13-00011-201 - LAK
A42: 1021.01.02 | B42: ເງິນຝາກກະແສລາຍວັນ - VTB - MSIG SOKXAY - 9190-0001-2846 - LAK | C42: 8 | D42: Y | E42: 1021.001 | F42: ? | G42: ? | H42: Current Accounts - VTB - MSIG SOKXAY - 9190-0001-2846 - LAK
A43: 1021.01.03 | B43: ເງິນຝາກກະແສລາຍວັນ - MRH - MSIG SOKXAY - 0381-1214-0001 - LAK | C43: 8 | D43: Y | E43: 1021.001 | F43: ? | G43: ? | H43: Current Accounts - MRH - MSIG SOKXAY - 0381-1214-0001 - LAK
A44: 1021.01.04 | B44: ເງິນຝາກກະແສລາຍວັນ - APB - MSIG SOKXAY - 0000-1001-1001-1850 - LAK | C44: 8 | D44: Y | E44: 1021.001 | F44: ? | G44: ? | H44: Current Accounts - APB - MSIG SOKXAY - 0000-1001-1001-1850 - LAK
A45: 1021.01.05 | B45: ເງິນຝາກກະແສລາຍວັນ -LDB - MSIG SOKXAY - 03020-00-010005252 - LAK | C45: 8 | D45: Y | E45: 1021.001 | F45: ? | G45: ? | H45: Current Accounts - LDB - MSIG SOKXAY - 03020-00-010005252 - LAK
A46: 1021.01.06 | B46: ເງິນຝາກກະແສລາຍວັນ - BCEL - SIC - 010-11-00-01445736-001 - LAK | C46: 8 | D46: Y | E46: 1021.001 | F46: ? | G46: ? | H46: Current Accounts - BCEL - SIC - 010-11-00-01445736-001 - LAK
A47: 1021.01.07 | B47: ເງິນຝາກກະແສລາຍວັນ - PSVB - SIC - 020-505-0001-498 - LAK | C47: 8 | D47: Y | E47: 1021.001 | F47: ? | G47: ? | H47: Current Accounts - PSVB - SIC - 020-505-0001-498 - LAK
A48: 1021.01.08 | B48: ເງິນຝາກກະແສລາຍວັນ - MRH - SIC - 0066-7506-0001 - LAK | C48: 8 | D48: Y | E48: 1021.001 | F48: ? | G48: ? | H48: Current Accounts - MRH - SIC - 0066-7506-0001 - LAK
A49: 1021.01.09 | B49: ເງິນຝາກກະແສລາຍວັນ - VTB - SIC - 9440-0000-0210 - LAK | C49: 8 | D49: Y | E49: 1021.001 | F49: ? | G49: ? | H49: Current Accounts - VTB - SIC - 9440-0000-0210 - LAK
A50: 1021.01.10 | B50: ເງິນຝາກກະແສລາຍວັນ - LDB - SIC - 0302-0000-1000-3549 - LAK | C50: 8 | D50: Y | E50: 1021.001 | F50: ? | G50: ? | H50: Current Accounts - LDB - SIC - 0302-0000-1000-3549 - LAK
A51: 1021.01.11 | B51: ເງິນຝາກກະແສລາຍວັນ - APB - SIC - 0000100-11-0005434 - LAK | C51: 8 | D51: Y | E51: 1021.001 | F51: ? | G51: ? | H51: Current Accounts - APB - SIC - 0000100-11-0005434 - LAK
A52: 1021.01.12 | B52: ເງິນຝາກກະແສລາຍວັນ - DTMI - SIC - 0901-00-213111-00-000000001 - LAK | C52: 8 | D52: Y | E52: 1021.001 | F52: ? | G52: ? | H52: Current Accounts - DTMI - SIC - 0901-00-213111-00-000000001 - LAK
... A59: 1021.01.19 | B59: ເງິນຝາກກະແສລາຍວັນ - LVB - MSIG SOKXAY - 010-00-12-0025314 - LAK | C59: 8 | D59: Y | E59: 1021.001 | F59: ? | G59: ? | H59: Current Accounts - LVB - MSIG SOKXAY - 010-00-12-0025314 - LAK
A60: 1021.02 | B60: ເງິນຝາກປະຢັດ | C60: 6 | D60: N | E60: 1021 | F60: ? | G60: ? | H60: Cash at Banks - Saving Accounts
A61: 1021.002 | B61: ເງິນຝາກປະຢັດ | C61: 7 | D61: N | E61: 1021.02 | F61: ? | G61: ? | H61: Cash at Banks - Saving Accounts
A62: 1021.02.01 | B62: ເງິນຝາກປະຢັດ - BCEL - MSIG L - 010-12-00-00485625-001 - LAK | C62: 8 | D62: Y | E62: 1021.002 | F62: ? | G62: ? | H62: Saving Accounts - BCEL - MSIG L - 010-12-00-00485625-001 - LAK
A63: 1021.02.03 | B63: ເງິນຝາກປະຢັດ - SMI - SIC - 01-1121-01-3532-03954 - LAK | C63: 8 | D63: Y | E63: 1021.002 | F63: ? | G63: ? | H63: Saving Accounts - SMI - SIC - 01-1121-01-3532-03954 - LAK
A64: 1021.03 | B64: ເງິນຝາກປະຈຳ | C64: 6 | D64: N | E64: 1021 | F64: ? | G64: ? | H64: Cash at Banks - Fixed Acounts
A65: 1021.003 | B65: ເງິນຝາກປະຈຳ | C65: 7 | D65: N | E65: 1021.03 | F65: ? | G65: ? | H65: Cash at Banks - Fixed Acounts
A66: 1021.03.01 | B66: ເງິນຝາກປະຈຳ - LVB - MSIG SOKXAY - 01500-1200-00280 - LAK | C66: 8 | D66: Y | E66: 1021.003 | F66: ? | G66: ? | H66: Fixed Accounts - LVB - MSIG SOKXAY - 01500-1200-00280 - LAK
A67: 1021.03.02 | B67: ເງິນຝາກປະຈຳ - BCEL - MSIG L - 0103-2000-0064-122001001 - LAK | C67: 8 | D67: Y | E67: 1021.003 | F67: ? | G67: ? | H67: Fixed Accounts - BCEL - MSIG L - 0103-2000-0064-122001001 - LAK
A68: 1021.03.03 | B68: ເງິນຝາກປະຈຳ - LDB - MSIG SOKXAY 0302000630001721 - LAK | C68: 8 | D68: Y | E68: 1021.003 | F68: ? | G68: ? | H68: Fixed Account - LDB - MSIG SOKXAY 03020-0063-0001721 - LAK
A69: 1021.03.04 | B69: ເງິນຝາກປະຈຳ - MRH - MSIG SOKXAY - 0381-1276-0001 - LAK | C69: 8 | D69: Y | E69: 1021.003 | F69: ? | G69: ? | H69: Fixed Account - MRH - MSIG SOKXAY - 0381-1276-0001 - LAK
A70: 1021.03.05 | B70: ເງິນຝາກປະຈຳ - LVB - MSIG SOKXAY - 010-00-32000-9994 - 6MONTHS - LAK | C70: 8 | D70: Y | E70: 1021.003 | F70: ? | G70: ? | H70: Fixed Account - LVB - MSIG SOKXAY - 010-00-32000-9994 - 6MONTHS - LAK
A71: 1022 | B71: ເງິນຝາກທະນາຄານ​ເປັນ​ເງິນຕາຕ່າງ​ປະ​ເທດ | C71: 5 | D71: N | E71: 102 | F71: ? | G71: ? | H71: Bank accounts in foreign currencies
A72: 1022.01 | B72: ເງິນຝາກທະນາຄານບັນຊີກະແສລາຍວັນ | C72: 6 | D72: N | E72: 1022 | F72: ? | G72: ? | H72: Cash at Banks - Current Accounts
A73: 1022.001 | B73: ເງິນຝາກທະນາຄານບັນຊີກະແສລາຍວັນ | C73: 7 | D73: N | E73: 1022.01 | F73: ? | G73: ? | H73: Cash at Banks - Current Accounts
A74: 1022.01.01 | B74: ເງິນຝາກກະແສລາຍວັນ - BCEL - MSIG SOKXAY - 010-13-00011-210 - THB | C74: 8 | D74: Y | E74: 1022.001 | F74: ? | G74: ? | H74: Current Accounts - BCEL - MSIG SOKXAY - 010-13-00011-210 - THB
A75: 1022.01.02 | B75: ເງິນຝາກກະແສລາຍວັນ - LDB - MSIG SOKXAY - 03020-02-010002326 - THB | C75: 8 | D75: Y | E75: 1022.001 | F75: ? | G75: ? | H75: Current Accounts - LDB - MSIG SOKXAY - 03020-02-010002326 - THB
A76: 1022.01.03 | B76: ເງິນຝາກກະແສລາຍວັນ - BCEL - MSIG SOKXAY - 010-13-00011-229 - USD | C76: 8 | D76: Y | E76: 1022.001 | F76: ? | G76: ? | H76: Current Accounts - BCEL - MSIG SOKXAY - 010-13-00011-229 - USD
A77: 1022.01.04 | B77: ເງິນຝາກກະແສລາຍວັນ - LDB - MSIG SOKXAY - 030200-10-10002306 - USD | C77: 8 | D77: Y | E77: 1022.001 | F77: ? | G77: ? | H77: Current Accounts - LDB - MSIG SOKXAY - 030200-10-10002306 - USD
A78: 1022.01.05 | B78: ເງິນຝາກກະແສລາຍວັນ - BCEL - SIC - 010-11-02-01445736-001 - THB | C78: 8 | D78: Y | E78: 1022.001 | F78: ? | G78: ? | H78: Current Accounts - BCEL - SIC - 010-11-02-01445736-001 - THB
A79: 1022.01.06 | B79: ເງິນຝາກກະແສລາຍວັນ - PSVB - SIC - 020-505-0201-395 - THB | C79: 8 | D79: Y | E79: 1022.001 | F79: ? | G79: ? | H79: Current Accounts - PSVB - SIC - 020-505-0201-395 - THB
A80: 1022.01.07 | B80: ເງິນຝາກກະແສລາຍວັນ - VTB - SIC - 9441-0000-0225 - THB | C80: 8 | D80: Y | E80: 1022.001 | F80: ? | G80: ? | H80: Current Accounts - VTB - SIC - 9441-0000-0225 - THB
A81: 1022.01.08 | B81: ເງິນຝາກກະແສລາຍວັນ - BIC - SIC - 0000-3010-0032-603 - THB | C81: 8 | D81: Y | E81: 1022.001 | F81: ? | G81: ? | H81: Current Accounts - BIC - SIC - 0000-3010-0032-603 - THB
A82: 1022.01.09 | B82: ເງິນຝາກກະແສລາຍວັນ - BCEL - MSIG L - 01011-0200184126-001 - THB | C82: 8 | D82: Y | E82: 1022.001 | F82: ? | G82: ? | H82: Current Accounts - BCEL - MSIG L - 01011-0200184126-001 - THB
A83: 1022.01.10 | B83: ເງິນຝາກກະແສລາຍວັນ - VTB - MSIG SOKXAY - 9170-0001-2848 - THB | C83: 8 | D83: Y | E83: 1022.001 | F83: ? | G83: ? | H83: Current Accounts - VTB - MSIG SOKXAY - 9170-0001-2848 - THB
A84: 1022.01.11 | B84: ເງິນຝາກກະແສລາຍວັນ - BCEL - SIC - 010-11-01-01445736-001 - USD | C84: 8 | D84: Y | E84: 1022.001 | F84: ? | G84: ? | H84: Current Accounts - BCEL - SIC - 010-11-01-01445736-001 - USD
A85: 1022.01.12 | B85: ເງິນຝາກກະແສລາຍວັນ - PSVB - SIC - 020-205-0101-593 - USD | C85: 8 | D85: Y | E85: 1022.001 | F85: ? | G85: ? | H85: Current Accounts - PSVB - SIC - 020-205-0101-593 - USD
... A95: 1022.01.22 | B95: ເງິນຝາກກະແສລາຍວັນ - ACD - MSIG SOKXAY - 346933-1-2 - USD | C95: 8 | D95: Y | E95: 1022.001 | F95: ? | G95: ? | H95: Current Accounts - ACD - MSIG SOKXAY - 346933-1-2 - USD
A96: 1022.02 | B96: ເງິນຝາກປະຢັດ | C96: 6 | D96: N | E96: 1022 | F96: ? | G96: ? | H96: Cash at Banks - Saving Accounts
A97: 1022.002 | B97: ເງິນຝາກປະຢັດ | C97: 7 | D97: N | E97: 1022.02 | F97: ? | G97: ? | H97: Cash at Banks - Saving Accounts
A98: 1022.02.01 | B98: ເງິນຝາກປະຢັດ - VTB - MSIG SOKXAY - 9100-0001-2939 - VND | C98: 8 | D98: Y | E98: 1022.002 | F98: ? | G98: ? | H98: Saving Accounts - VTB - MSIG SOKXAY - 9100-0001-2939 - VND
A99: 1022.02.02 | B99: ເງິນຝາກປະຢັດ - MRH - MSIG SOKXAY - 03811-2140-101 - USD | C99: 8 | D99: Y | E99: 1022.002 | F99: ? | G99: ? | H99: Saving Accounts - MRH - MSIG SOKXAY - 03811-2140-101 - USD
A100: 1022.03 | B100: ເງິນຝາກປະຈຳ | C100: 6 | D100: N | E100: 1022 | F100: ? | G100: ? | H100: Cash at Banks - Fixed Acounts
A101: 1022.003 | B101: ເງິນຝາກປະຈຳ | C101: 7 | D101: N | E101: 1022.03 | F101: ? | G101: ? | H101: Cash at Banks - Fixed Acounts
A102: 1022.03.01 | B102: ເງິນຝາກປະຈຳ - LDB - MSIG SOKXAY - 030200-01-630000164 - USD | C102: 8 | D102: Y | E102: 1022.003 | F102: ? | G102: ? | H102: Fixed Accounts - LDB - MSIG SOKXAY - 030200-01-630000164 - USD
A103: 1022.03.02 | B103: ເງິນຝາກປະຈຳ - ANZ - MSIG L - 702225-26674 - USD | C103: 8 | D103: Y | E103: 1022.003 | F103: ? | G103: ? | H103: Fixed Accounts - ANZ - MSIG L - 702225-26674 - USD
A104: 1022.03.03 | B104: ເງິນຝາກປະຈຳ - LDB - MSIG SOKXAY - 030200-1600-000164 - USD | C104: 8 | D104: Y | E104: 1022.003 | F104: ? | G104: ? | H104: Fixed Accounts - LDB - MSIG SOKXAY - 030200-1600-000164 - USD
A105: 1022.03.04 | B105: ເງິນຝາກປະຈຳ - MRH - MSIG SOKXAY - 0381-1276-0101 - USD | C105: 8 | D105: Y | E105: 1022.003 | F105: ? | G105: ? | H105: Fixed Accounts - MRH - MSIG SOKXAY - 0381-1276-0101 - USD
A106: 1022.04.01 | B106: ເງິນຝາກປະຈຳ - | C106: 7 | D106: N | E106: 1022.03 | F106: ? | G106: ? | H106: Fixed Accounts -
A107: 1023 | B107: ​ເງິນ​ຝາກຄັງເງິນແຫ່ງຊາດ | C107: 5 | D107: N | E107: 102 | F107: ? | G107: ? | H107: National treasury
A108: 1024 | B108: ເງິນ​ຝາກສະ​ຖາບັນ​ການ​ເງິນ​ອື່ນໆ | C108: 5 | D108: N | E108: 102 | F108: ? | G108: ? | H108: Other financial institutions
A109: 1024.01 | B109: ເງິນຝາກທະນາຄານບັນຊີກະແສລາຍວັນ | C109: 6 | D109: N | E109: 1024 | F109: ? | G109: ? | H109: Cash at Banks - Current Accounts
A110: 1024.02 | B110: ເງິນຝາກປະຢັດ | C110: 6 | D110: N | E110: 1024 | F110: ? | G110: ? | H110: Cash at Banks - Saving Accounts
A111: 1024.020 | B111: ເງິນຝາກປະຢັດ | C111: 7 | D111: N | E111: 1024.02 | F111: ? | G111: ? | H111: Cash at Banks - Saving Accounts
A112: 1024.02.01 | B112: ເງິນຝາກປະຢັດ - SMI - MSIG SOKXAY - 01-1121-01-11134-11309 - LAK | C112: 8 | D112: Y | E112: 1024.02 | F112: ? | G112: ? | H112: Saving Accounts - SMI - MSIG SOKXAY - 01-1121-01-11134-11309 - LAK
A113: 1024.02.02 | B113: ເງິນຝາກປະຢັດ - SMI - SIC - 01-1121-01-5585-05268 - LAK | C113: 8 | D113: Y | E113: 1024.02 | F113: ? | G113: ? | H113: Saving Accounts - SMI - SIC - 01-1121-01-5585-05268 - LAK
A114: 1024.03 | B114: ເງິນຝາກປະຈຳ | C114: 6 | D114: N | E114: 1024
A115: 1024.003 | B115: ເງິນຝາກປະຈຳ | C115: 7 | D115: N | E115: 1024.03 | F115: ? | G115: ? | H115: Cash at Banks - Fixed Acounts
...

Sheet COA_MSIGSX 09.02.2026
A1: Code | B1: Name | C1: ActiveAccount | D1: FatherAccountKey | E1: U_TypeProduct | F1: U_Channel | G1: U_ForeignName | H1: U_Grouping
A2: AcctCode | B2: AcctName | C2: Postable | D2: FatherNum | E2: U_TypeProduct | F2: U_Channel | G2: U_ForeignName | H2: U_Grouping
A3: 1 | B3: ບັນຊີ ປະເພດ 1 – ບັນ​ດາ ບັນຊີ ຊັບ​ສິນ​ໝູນ​ວຽນ | C3: tNO | D3: 100000000000000 | G3: CLASS 1 – CURRENT ASSETS | H3: =VLOOKUP(A3,COA!$A:$H,8,FALSE) -> CLASS 1 – CURRENT ASSETS
A4: 10 | B4: ເງິນສົດໃນ​ຄັງ, ເງິນ​ຍ່ອຍ, ເງິນຝາກທຄ, ສະ​ຖາ​ບັນ​ການ​ເງິນ, ເງິນ​ຝາກ​ຄັງ​ເງິນ​ແຫ່ງ​ຊາດ | C4: tNO | D4: 1 | G4: Cash on Hand, Petty Cash, Cash in Banks, Financial Institutions and National Treasury | H4: =VLOOKUP(A4,COA!$A:$H,8,FALSE) -> Cash on Hand, Petty Cash, Cash in Banks, Financial Institutions and National Treasury
A5: 101 | B5: ​ເງິນສົດ​ໃນ​ຄັງ | C5: tNO | D5: 10 | G5: ​Cash on Hand | H5: =VLOOKUP(A5,COA!$A:$H,8,FALSE) -> ​Cash on Hand
A6: 1011 | B6: ​ເງິນສົດ​ເປັນ​ເງິນກີບ | C6: tNO | D6: 101 | G6: Cash on hand – Kip | H6: =VLOOKUP(A6,COA!$A:$H,8,FALSE) -> Cash on hand – Kip
A7: 1011.01 | B7: ເງິນສົດຄັງຍ່ອຍ | C7: tNO | D7: 1011 | G7: Cash of Sub Branch | H7: =VLOOKUP(A7,COA!$A:$H,8,FALSE) -> Cash of Sub Branch
A8: 1011.001 | B8: ເງິນສົດຄັງຍ່ອຍ | C8: tNO | D8: 1011.01 | G8: Cash of Sub Branch | H8: =VLOOKUP(A8,COA!$A:$H,8,FALSE) -> Cash of Sub Branch
A9: 1011.01.00 | B9: ເງິນສົດຍ່ອຍ-ກີບ | C9: tYES | D9: 1011.001 | G9: Cash on hand-LAK | H9: =VLOOKUP(A9,COA!$A:$H,8,FALSE) -> Cash on hand - LAK
A10: 1011.01.01 | B10: ເງິນສົດຍ່ອຍ-ໂດລາ | C10: tYES | D10: 1011.001 | G10: Cash on hand-USD | H10: =VLOOKUP(A10,COA!$A:$H,8,FALSE) -> Cash on hand - USD
A11: 1011.01.02 | B11: ເງິນສົດຍ່ອຍ-ບາດ | C11: tYES | D11: 1011.001 | G11: Cash on hand-THB | H11: =VLOOKUP(A11,COA!$A:$H,8,FALSE) -> Cash on hand - THB
A12: 1011.01.03 | B12: ເງິນສົດຍ່ອຍ-ອື່ນໆ | C12: tYES | D12: 1011.001 | G12: Cash on hand – Other | H12: =VLOOKUP(A12,COA!$A:$H,8,FALSE) -> Cash on hand – Other
A13: 1012 | B13: ເງິນສົດ​ເປັນ​ເງິນ​ຕາ​ຕ່າງ​ປະ​ເທດ | C13: tNO | D13: 101 | G13: Cash on hand – Foreign currencies | H13: =VLOOKUP(A13,COA!$A:$H,8,FALSE) -> Cash on hand – Foreign currencies
A14: 1013 | B14: ເງິນ​ສົດ​ຍ່ອຍ | C14: tNO | D14: 101 | G14: Petty cash | H14: =VLOOKUP(A14,COA!$A:$H,8,FALSE) -> Petty cash
A15: 1013 | B15: ເງິນ​ສົດ​ຍ່ອຍ | C15: tNO | D15: 1013 | G15: Petty cash | H15: =VLOOKUP(A15,COA!$A:$H,8,FALSE) -> Petty cash
A16: 1013 | B16: ເງິນສົດໃນມື-ກີບ | C16: tNO | D16: 1013.0 | G16: Petty cash-LAK | H16: =VLOOKUP(A16,COA!$A:$H,8,FALSE) -> Petty cash
A17: 1013.001 | B17: ເງິນສົດໃນມື-ກີບ | C17: tYES | D17: 1013.00 | G17: Petty cash-LAK | H17: =VLOOKUP(A17,COA!$A:$H,8,FALSE) -> Petty cash - LAK
A18: 1013.01 | B18: ເງິນສົດໃນມື-ໂດລາ | C18: tYES | D18: 1013.00 | G18: Petty Cash-USD | H18: =VLOOKUP(A18,COA!$A:$H,8,FALSE) -> Petty Cash - USD
A19: 1013.02 | B19: ເງິນສົດໃນມື-ບາດ | C19: tYES | D19: 1013.00 | G19: Petty Cash-THB | H19: =VLOOKUP(A19,COA!$A:$H,8,FALSE) -> Petty Cash - THB
A20: 1013.03 | B20: ເງິນສົດໃນມື-ອື່ນໆ | C20: tYES | D20: 1013.00 | G20: Petty Cash-Other | H20: =VLOOKUP(A20,COA!$A:$H,8,FALSE) -> Petty Cash - Other
A21: 1014 | B21: ເງິນສົດກຳລັງນຳຝາກ-ທຄບໍ່ທັນໄດ້ຈົດເຂົ້າບັນຊີ | C21: tNO | D21: 101 | G21: Cash in transit – not yet recorded in banks’ accounting | H21: =VLOOKUP(A21,COA!$A:$H,8,FALSE) -> Cash in transit – not yet recorded in banks’ accounting
A22: 1017 | B22: ລ່ວງໜ້າ​ເງິນ​ສົດ | C22: tNO | D22: 101 | G22: Cash advance | H22: =VLOOKUP(A22,COA!$A:$H,8,FALSE) -> Cash advance
A23: 1017.01 | B23: ເງິນເບີກລ່ວງໜ້າ | C23: tNO | D23: 1017 | G23: Advances | H23: =VLOOKUP(A23,COA!$A:$H,8,FALSE) -> Advances
A24: 1017.02 | B24: ແບ່ງສ່ວນຈ່າຍອາກອນລາຍໄດ້ຫັກຕອນທີ່ຈ່າຍ | C24: tNO | D24: 1017 | G24: Prepaid Withholding Tax | H24: =VLOOKUP(A24,COA!$A:$H,8,FALSE) -> Prepaid Withholding Tax
A25: 1017.03 | B25: ເງິນມັດຈຳ | C25: tNO | D25: 1017 | G25: Deposits | H25: =VLOOKUP(A25,COA!$A:$H,8,FALSE) -> Deposits
A26: 1017.003 | B26: ເງິນມັດຈຳ | C26: tNO | D26: 1017.03 | G26: Deposits | H26: =VLOOKUP(A26,COA!$A:$H,8,FALSE) -> Deposits
A27: 1017.03.01 | B27: ເງິນມັດຈຳ ບັດນໍ້າມັນ | C27: tYES | D27: 1017.003 | G27: Deposits Plus Card | H27: =VLOOKUP(A27,COA!$A:$H,8,FALSE) -> Deposits Plus Card
A28: 1017.04 | B28: ແຊັກສັ່ງຈ່າຍລ່ວງໜ້າ | C28: tNO | D28: 1017 | G28: Post Dated Cheque | H28: =VLOOKUP(A28,COA!$A:$H,8,FALSE) -> Post Dated Cheque
A29: 1017.05 | B29: ຈ່າຍລ່ວງໜ້າ (ມັດຈຳ) | C29: tNO | D29: 1017 | G29: Prepayment | H29: =VLOOKUP(A29,COA!$A:$H,8,FALSE) -> Prepayment
A30: 1017.06 | B30: ຈ່າຍລ່ວງໜ້າ | C30: tNO | D30: 1017 | G30: Prepaid-Expense | H30: =VLOOKUP(A30,COA!$A:$H,8,FALSE) -> Prepaid - Expense
A31: 1017.07 | B31: ຈ່າຍລ່ວງໜ້າ-ຜົນຕອບແທນໃຫ້ຕົວແທນ | C31: tNO | D31: 1017 | G31: Prepayment-Commission Due to Agent | H31: =VLOOKUP(A31,COA!$A:$H,8,FALSE) -> Prepayment - Commission Due to Agent
A32: 1017.08 | B32: ໜີ້ຕ້ອງສົ່ງ ອາກອນສົ້ນເຂົ້າ ປກພ ຕໍ່ | C32: tNO | D32: 1017 | G32: Value Added Tax-Input Tax for Reinsurance Ceed | H32: =VLOOKUP(A32,COA!$A:$H,8,FALSE) -> Value Added Tax - Input Tax for Reinsurance Ceed
A33: 1017.09 | B33: ສ່ວນຫຼຸດໃນການຊື້ ອື່ນໆ | C33: tNO | D33: 1017 | G33: Purchase rebates, discounts, allowances | H33: =VLOOKUP(A33,COA!$A:$H,8,FALSE) -> Purchase rebates, discounts, allowances
A34: 1017.10 | B34: ອາກອນມູນຄ່າເພີ່ມລາຍຈ່າຍ | C34: tNO | D34: 1017 | G34: Value added taxies. Expenditure 07% | H34: =VLOOKUP(A34,COA!$A:$H,8,FALSE) -> Value added taxies. Expenditure 07%
A35: 1017.11 | B35: ອາກອນມູນຄ່າເພີ່ມຫັກໃນເດືອນກ່ອນຍັງບໍ່ໝົດ | C35: tNO | D35: 1017 | G35: Value added taies that was not fully deducted from the previous months | H35: =VLOOKUP(A35,COA!$A:$H,8,FALSE) -> Value added taies that was not fully deducted from the previous months
A36: 1017.12 | B36: ໜ້າຕ້ອງຮັບ MSITB | C36: tNO | D36: 1017 | G36: Account Receivable for MSITB | H36: =VLOOKUP(A36,COA!$A:$H,8,FALSE) -> Account Receivable for MSITB
A37: 1017.13 | B37: ໜີ້ຕ້ອງຮັບ ເງິນຝາກຄໍ້າປະກັນ | C37: tNO | D37: 1017 | G37: Account receivable for Security Deposit to Bank | H37: =VLOOKUP(A37,COA!$A:$H,8,FALSE) -> Account receivable for Security Deposit to Bank
A38: 102 | B38: ເງິນຝາກທຄ, ສະຖາບັນການເງິນ ແລະ ສະ​ຖາ​ບັນ​ທີ່​ຄ້າຍ​ຄື​ກັນ" | C38: tNO | D38: 10 | G38: Banks, Financial and Similar Institutions | H38: =VLOOKUP(A38,COA!$A:$H,8,FALSE) -> Banks, Financial and Similar Institutions
A39: 1021 | B39: ເງິນຝາກທຄເປັນ​ເງິນ​ກີບ | C39: tNO | D39: 102 | G39: Bank accounts in Kip | H39: =VLOOKUP(A39,COA!$A:$H,8,FALSE) -> Bank accounts in Kip
A40: 1021.01 | B40: ເງິນຝາກທຄບັນຊີກະແສລາຍວັນ | C40: tNO | D40: 1021 | G40: Cash at Banks-Current Accounts | H40: =VLOOKUP(A40,COA!$A:$H,8,FALSE) -> Cash at Banks - Current Accounts
A41: 1021.001 | B41: ເງິນຝາກທຄບັນຊີກະແສລາຍວັນ | C41: tNO | D41: 1021.01 | G41: Cash at Banks-Current Accounts | H41: =VLOOKUP(A41,COA!$A:$H,8,FALSE) -> Cash at Banks - Current Accounts
A42: 1021.01.01 | B42: ເງິນຝາກກະແສລາຍວັນ-BCEL-MSIG SOKXAY-010-13-00011-201-LAK | C42: tYES | D42: 1021.001 | G42: Current Accounts-BCEL-MSIG SOKXAY-010-13-00011-201-LAK | H42: =VLOOKUP(A42,COA!$A:$H,8,FALSE) -> Current Accounts - BCEL - MSIG SOKXAY - 010-13-00011-201 - LAK
A43: 1021.01.02 | B43: ເງິນຝາກກະແສລາຍວັນ-VTB-MSIG SOKXAY-9190-0001-2846-LAK | C43: tYES | D43: 1021.001 | G43: Current Accounts-VTB-MSIG SOKXAY-9190-0001-2846-LAK | H43: =VLOOKUP(A43,COA!$A:$H,8,FALSE) -> Current Accounts - VTB - MSIG SOKXAY - 9190-0001-2846 - LAK
A44: 1021.01.03 | B44: ເງິນຝາກກະແສລາຍວັນ-MRH-MSIG SOKXAY-0381-1214-0001-LAK | C44: tYES | D44: 1021.001 | G44: Current Accounts-MRH-MSIG SOKXAY-0381-1214-0001-LAK | H44: =VLOOKUP(A44,COA!$A:$H,8,FALSE) -> Current Accounts - MRH - MSIG SOKXAY - 0381-1214-0001 - LAK
A45: 1021.01.04 | B45: ເງິນຝາກກະແສລາຍວັນ-APB-MSIG SOKXAY-0000-1001-1001-1850-LAK | C45: tYES | D45: 1021.001 | G45: Current Accounts-APB-MSIG SOKXAY-0000-1001-1001-1850-LAK | H45: =VLOOKUP(A45,COA!$A:$H,8,FALSE) -> Current Accounts - APB - MSIG SOKXAY - 0000-1001-1001-1850 - LAK
A46: 1021.01.05 | B46: ເງິນຝາກກະແສລາຍວັນ -LDB-MSIG SOKXAY-03020-00-010005252-LAK | C46: tYES | D46: 1021.001 | G46: Current Accounts-LDB-MSIG SOKXAY-03020-00-010005252-LAK | H46: =VLOOKUP(A46,COA!$A:$H,8,FALSE) -> Current Accounts - LDB - MSIG SOKXAY - 03020-00-010005252 - LAK
A47: 1021.01.06 | B47: ເງິນຝາກກະແສລາຍວັນ-BCEL-SIC-010-11-00-01445736-001-LAK | C47: tYES | D47: 1021.001 | G47: Current Accounts-BCEL-SIC-010-11-00-01445736-001-LAK | H47: =VLOOKUP(A47,COA!$A:$H,8,FALSE) -> Current Accounts - BCEL - SIC - 010-11-00-01445736-001 - LAK
A48: 1021.01.07 | B48: ເງິນຝາກກະແສລາຍວັນ-PSVB-SIC-020-505-0001-498-LAK | C48: tYES | D48: 1021.001 | G48: Current Accounts-PSVB-SIC-020-505-0001-498-LAK | H48: =VLOOKUP(A48,COA!$A:$H,8,FALSE) -> Current Accounts - PSVB - SIC - 020-505-0001-498 - LAK
A49: 1021.01.08 | B49: ເງິນຝາກກະແສລາຍວັນ-MRH-SIC-0066-7506-0001-LAK | C49: tYES | D49: 1021.001 | G49: Current Accounts-MRH-SIC-0066-7506-0001-LAK | H49: =VLOOKUP(A49,COA!$A:$H,8,FALSE) -> Current Accounts - MRH - SIC - 0066-7506-0001 - LAK
A50: 1021.01.09 | B50: ເງິນຝາກກະແສລາຍວັນ-VTB-SIC-9440-0000-0210-LAK | C50: tYES | D50: 1021.001 | G50: Current Accounts-VTB-SIC-9440-0000-0210-LAK | H50: =VLOOKUP(A50,COA!$A:$H,8,FALSE) -> Current Accounts - VTB - SIC - 9440-0000-0210 - LAK
A51: 1021.01.10 | B51: ເງິນຝາກກະແສລາຍວັນ-LDB-SIC-0302-0000-1000-3549-LAK | C51: tYES | D51: 1021.001 | G51: Current Accounts-LDB-SIC-0302-0000-1000-3549-LAK | H51: =VLOOKUP(A51,COA!$A:$H,8,FALSE) -> Current Accounts - LDB - SIC - 0302-0000-1000-3549 - LAK
A52: 1021.01.11 | B52: ເງິນຝາກກະແສລາຍວັນ-APB-SIC-0000100-11-0005434-LAK | C52: tYES | D52: 1021.001 | G52: Current Accounts-APB-SIC-0000100-11-0005434-LAK | H52: =VLOOKUP(A52,COA!$A:$H,8,FALSE) -> Current Accounts - APB - SIC - 0000100-11-0005434 - LAK
A53: 1021.01.12 | B53: ເງິນຝາກກະແສລາຍວັນ-DTMI-SIC-0901-00-213111-00-000000001-LAK | C53: tYES | D53: 1021.001 | G53: Current Accounts-DTMI-SIC-0901-00-213111-00-000000001-LAK | H53: =VLOOKUP(A53,COA!$A:$H,8,FALSE) -> Current Accounts - DTMI - SIC - 0901-00-213111-00-000000001 - LAK
... A60: 1021.01.19 | B60: ເງິນຝາກກະແສລາຍວັນ-LVB-MSIG SOKXAY-010-00-12-0025314-LAK | C60: tYES | D60: 1021.001 | G60: Current Accounts-LVB-MSIG SOKXAY-010-00-12-0025314-LAK | H60: =VLOOKUP(A60,COA!$A:$H,8,FALSE) -> Current Accounts - LVB - MSIG SOKXAY - 010-00-12-0025314 - LAK
A61: 1021.02 | B61: ເງິນຝາກປະຢັດ | C61: tNO | D61: 1021 | G61: Cash at Banks-Saving Accounts | H61: =VLOOKUP(A61,COA!$A:$H,8,FALSE) -> Cash at Banks - Saving Accounts
A62: 1021.002 | B62: ເງິນຝາກປະຢັດ | C62: tNO | D62: 1021.02 | G62: Cash at Banks-Saving Accounts | H62: =VLOOKUP(A62,COA!$A:$H,8,FALSE) -> Cash at Banks - Saving Accounts
A63: 1021.02.01 | B63: ເງິນຝາກປະຢັດ-BCEL-MSIG L-010-12-00-00485625-001-LAK | C63: tYES | D63: 1021.002 | G63: Saving Accounts-BCEL-MSIG L-010-12-00-00485625-001-LAK | H63: =VLOOKUP(A63,COA!$A:$H,8,FALSE) -> Saving Accounts - BCEL - MSIG L - 010-12-00-00485625-001 - LAK
A64: 1021.02.03 | B64: ເງິນຝາກປະຢັດ-SMI-SIC-01-1121-01-3532-03954-LAK | C64: tYES | D64: 1021.002 | G64: Saving Accounts-SMI-SIC-01-1121-01-3532-03954-LAK | H64: =VLOOKUP(A64,COA!$A:$H,8,FALSE) -> Saving Accounts - SMI - SIC - 01-1121-01-3532-03954 - LAK
A65: 1021.03 | B65: ເງິນຝາກປະຈຳ | C65: tNO | D65: 1021 | G65: Cash at Banks-Fixed Acounts | H65: =VLOOKUP(A65,COA!$A:$H,8,FALSE) -> Cash at Banks - Fixed Acounts
A66: 1021.003 | B66: ເງິນຝາກປະຈຳ | C66: tNO | D66: 1021.03 | G66: Cash at Banks-Fixed Acounts | H66: =VLOOKUP(A66,COA!$A:$H,8,FALSE) -> Cash at Banks - Fixed Acounts
A67: 1021.03.01 | B67: ເງິນຝາກປະຈຳ-LVB-MSIG SOKXAY-01500-1200-00280-LAK | C67: tYES | D67: 1021.003 | G67: Fixed Accounts-LVB-MSIG SOKXAY-01500-1200-00280-LAK | H67: =VLOOKUP(A67,COA!$A:$H,8,FALSE) -> Fixed Accounts - LVB - MSIG SOKXAY - 01500-1200-00280 - LAK
A68: 1021.03.02 | B68: ເງິນຝາກປະຈຳ-BCEL-MSIG L-0103-2000-0064-122001001-LAK | C68: tYES | D68: 1021.003 | G68: Fixed Accounts-BCEL-MSIG L-0103-2000-0064-122001001-LAK | H68: =VLOOKUP(A68,COA!$A:$H,8,FALSE) -> Fixed Accounts - BCEL - MSIG L - 0103-2000-0064-122001001 - LAK
A69: 1021.03.03 | B69: ເງິນຝາກປະຈຳ-LDB-MSIG SOKXAY 0302000630001721-LAK | C69: tYES | D69: 1021.003 | G69: Fixed Account-LDB-MSIG SOKXAY 03020-0063-0001721-LAK | H69: =VLOOKUP(A69,COA!$A:$H,8,FALSE) -> Fixed Account - LDB - MSIG SOKXAY 03020-0063-0001721 - LAK
A70: 1021.03.04 | B70: ເງິນຝາກປະຈຳ-MRH-MSIG SOKXAY-0381-1276-0001-LAK | C70: tYES | D70: 1021.003 | G70: Fixed Account-MRH-MSIG SOKXAY-0381-1276-0001-LAK | H70: =VLOOKUP(A70,COA!$A:$H,8,FALSE) -> Fixed Account - MRH - MSIG SOKXAY - 0381-1276-0001 - LAK
A71: 1021.03.05 | B71: ເງິນຝາກປະຈຳ-LVB-MSIG SOKXAY-010-00-32000-9994-6MONTHS-LAK | C71: tYES | D71: 1021.003 | G71: Fixed Account-LVB-MSIG SOKXAY-010-00-32000-9994-6MONTHS-LAK | H71: =VLOOKUP(A71,COA!$A:$H,8,FALSE) -> Fixed Account - LVB - MSIG SOKXAY - 010-00-32000-9994 - 6MONTHS - LAK
A72: 1022 | B72: ເງິນຝາກທຄ​ເປັນ​ເງິນຕາຕ່າງ​ປະ​ເທດ | C72: tNO | D72: 102 | G72: Bank accounts in foreign currencies | H72: =VLOOKUP(A72,COA!$A:$H,8,FALSE) -> Bank accounts in foreign currencies
A73: 1022.01 | B73: ເງິນຝາກທຄບັນຊີກະແສລາຍວັນ | C73: tNO | D73: 1022 | G73: Cash at Banks-Current Accounts | H73: =VLOOKUP(A73,COA!$A:$H,8,FALSE) -> Cash at Banks - Current Accounts
A74: 1022.001 | B74: ເງິນຝາກທຄບັນຊີກະແສລາຍວັນ | C74: tNO | D74: 1022.01 | G74: Cash at Banks-Current Accounts | H74: =VLOOKUP(A74,COA!$A:$H,8,FALSE) -> Cash at Banks - Current Accounts
A75: 1022.01.01 | B75: ເງິນຝາກກະແສລາຍວັນ-BCEL-MSIG SOKXAY-010-13-00011-210-THB | C75: tYES | D75: 1022.001 | G75: Current Accounts-BCEL-MSIG SOKXAY-010-13-00011-210-THB | H75: =VLOOKUP(A75,COA!$A:$H,8,FALSE) -> Current Accounts - BCEL - MSIG SOKXAY - 010-13-00011-210 - THB
A76: 1022.01.02 | B76: ເງິນຝາກກະແສລາຍວັນ-LDB-MSIG SOKXAY-03020-02-010002326-THB | C76: tYES | D76: 1022.001 | G76: Current Accounts-LDB-MSIG SOKXAY-03020-02-010002326-THB | H76: =VLOOKUP(A76,COA!$A:$H,8,FALSE) -> Current Accounts - LDB - MSIG SOKXAY - 03020-02-010002326 - THB
A77: 1022.01.03 | B77: ເງິນຝາກກະແສລາຍວັນ-BCEL-MSIG SOKXAY-010-13-00011-229-USD | C77: tYES | D77: 1022.001 | G77: Current Accounts-BCEL-MSIG SOKXAY-010-13-00011-229-USD | H77: =VLOOKUP(A77,COA!$A:$H,8,FALSE) -> Current Accounts - BCEL - MSIG SOKXAY - 010-13-00011-229 - USD
A78: 1022.01.04 | B78: ເງິນຝາກກະແສລາຍວັນ-LDB-MSIG SOKXAY-030200-10-10002306-USD | C78: tYES | D78: 1022.001 | G78: Current Accounts-LDB-MSIG SOKXAY-030200-10-10002306-USD | H78: =VLOOKUP(A78,COA!$A:$H,8,FALSE) -> Current Accounts - LDB - MSIG SOKXAY - 030200-10-10002306 - USD
A79: 1022.01.05 | B79: ເງິນຝາກກະແສລາຍວັນ-BCEL-SIC-010-11-02-01445736-001-THB | C79: tYES | D79: 1022.001 | G79: Current Accounts-BCEL-SIC-010-11-02-01445736-001-THB | H79: =VLOOKUP(A79,COA!$A:$H,8,FALSE) -> Current Accounts - BCEL - SIC - 010-11-02-01445736-001 - THB
A80: 1022.01.06 | B80: ເງິນຝາກກະແສລາຍວັນ-PSVB-SIC- 020-505-0201-395-THB | C80: tYES | D80: 1022.001 | G80: Current Accounts-PSVB-SIC-020-505-0201-395-THB | H80: =VLOOKUP(A80,COA!$A:$H,8,FALSE) -> Current Accounts - PSVB - SIC - 020-505-0201-395 - THB
A81: 1022.01.07 | B81: ເງິນຝາກກະແສລາຍວັນ-VTB-SIC-9441-0000-0225-THB | C81: tYES | D81: 1022.001 | G81: Current Accounts-VTB-SIC-9441-0000-0225-THB | H81: =VLOOKUP(A81,COA!$A:$H,8,FALSE) -> Current Accounts - VTB - SIC - 9441-0000-0225 - THB
A82: 1022.01.08 | B82: ເງິນຝາກກະແສລາຍວັນ-BIC-SIC-0000-3010-0032-603-THB | C82: tYES | D82: 1022.001 | G82: Current Accounts-BIC-SIC-0000-3010-0032-603-THB | H82: =VLOOKUP(A82,COA!$A:$H,8,FALSE) -> Current Accounts - BIC - SIC - 0000-3010-0032-603 - THB
A83: 1022.01.09 | B83: ເງິນຝາກກະແສລາຍວັນ-BCEL-MSIG L-01011-0200184126-001 -THB | C83: tYES | D83: 1022.001 | G83: Current Accounts-BCEL-MSIG L-01011-0200184126-001-THB | H83: =VLOOKUP(A83,COA!$A:$H,8,FALSE) -> Current Accounts - BCEL - MSIG L - 01011-0200184126-001 - THB
A84: 1022.01.10 | B84: ເງິນຝາກກະແສລາຍວັນ-VTB-MSIG SOKXAY-9170-0001-2848-THB | C84: tYES | D84: 1022.001 | G84: Current Accounts-VTB-MSIG SOKXAY-9170-0001-2848-THB | H84: =VLOOKUP(A84,COA!$A:$H,8,FALSE) -> Current Accounts - VTB - MSIG SOKXAY - 9170-0001-2848 - THB
A85: 1022.01.11 | B85: ເງິນຝາກກະແສລາຍວັນ-BCEL-SIC-010-11-01-01445736-001-USD | C85: tYES | D85: 1022.001 | G85: Current Accounts-BCEL-SIC-010-11-01-01445736-001-USD | H85: =VLOOKUP(A85,COA!$A:$H,8,FALSE) -> Current Accounts - BCEL - SIC - 010-11-01-01445736-001 - USD
A86: 1022.01.12 | B86: ເງິນຝາກກະແສລາຍວັນ-PSVB-SIC-020-205-0101-593-USD | C86: tYES | D86: 1022.001 | G86: Current Accounts-PSVB-SIC-020-205-0101-593-USD | H86: =VLOOKUP(A86,COA!$A:$H,8,FALSE) -> Current Accounts - PSVB - SIC - 020-205-0101-593 - USD
... A96: 1022.01.22 | B96: ເງິນຝາກກະແສລາຍວັນ-ACD-MSIG SOKXAY-346933-1-2-USD | C96: tYES | D96: 1022.001 | G96: Current Accounts-ACD-MSIG SOKXAY-346933-1-2-USD | H96: =VLOOKUP(A96,COA!$A:$H,8,FALSE) -> Current Accounts - ACD - MSIG SOKXAY - 346933-1-2 - USD
A97: 1022.02 | B97: ເງິນຝາກປະຢັດ | C97: tNO | D97: 1022 | G97: Cash at Banks-Saving Accounts | H97: =VLOOKUP(A97,COA!$A:$H,8,FALSE) -> Cash at Banks - Saving Accounts
A98: 1022.002 | B98: ເງິນຝາກປະຢັດ | C98: tNO | D98: 1022.02 | G98: Cash at Banks-Saving Accounts | H98: =VLOOKUP(A98,COA!$A:$H,8,FALSE) -> Cash at Banks - Saving Accounts
A99: 1022.02.01 | B99: ເງິນຝາກປະຢັດ-VTB-MSIG SOKXAY-9100-0001-2939 -VND | C99: tYES | D99: 1022.002 | G99: Saving Accounts-VTB-MSIG SOKXAY-9100-0001-2939-VND | H99: =VLOOKUP(A99,COA!$A:$H,8,FALSE) -> Saving Accounts - VTB - MSIG SOKXAY - 9100-0001-2939 - VND
A100: 1022.02.02 | B100: ເງິນຝາກປະຢັດ-MRH-MSIG SOKXAY-03811-2140-101-USD | C100: tYES | D100: 1022.002 | G100: Saving Accounts-MRH-MSIG SOKXAY-03811-2140-101-USD | H100: =VLOOKUP(A100,COA!$A:$H,8,FALSE) -> Saving Accounts - MRH - MSIG SOKXAY - 03811-2140-101 - USD
A101: 1022.03 | B101: ເງິນຝາກປະຈຳ | C101: tNO | D101: 1022 | G101: Cash at Banks-Fixed Acounts | H101: =VLOOKUP(A101,COA!$A:$H,8,FALSE) -> Cash at Banks - Fixed Acounts
A102: 1022.003 | B102: ເງິນຝາກປະຈຳ | C102: tNO | D102: 1022.03 | G102: Cash at Banks-Fixed Acounts | H102: =VLOOKUP(A102,COA!$A:$H,8,FALSE) -> Cash at Banks - Fixed Acounts
A103: 1022.03.01 | B103: ເງິນຝາກປະຈຳ-LDB-MSIG SOKXAY-030200-01-630000164-USD | C103: tYES | D103: 1022.003 | G103: Fixed Accounts-LDB-MSIG SOKXAY-030200-01-630000164-USD | H103: =VLOOKUP(A103,COA!$A:$H,8,FALSE) -> Fixed Accounts - LDB - MSIG SOKXAY - 030200-01-630000164 - USD
A104: 1022.03.02 | B104: ເງິນຝາກປະຈຳ-ANZ-MSIG L-702225-26674-USD | C104: tYES | D104: 1022.003 | G104: Fixed Accounts-ANZ-MSIG L-702225-26674-USD | H104: =VLOOKUP(A104,COA!$A:$H,8,FALSE) -> Fixed Accounts - ANZ - MSIG L - 702225-26674 - USD
A105: 1022.03.03 | B105: ເງິນຝາກປະຈຳ-LDB-MSIG SOKXAY-030200-1600-000164-USD | C105: tYES | D105: 1022.003 | G105: Fixed Accounts-LDB-MSIG SOKXAY-030200-1600-000164-USD | H105: =VLOOKUP(A105,COA!$A:$H,8,FALSE) -> Fixed Accounts - LDB - MSIG SOKXAY - 030200-1600-000164 - USD
A106: 1022.03.04 | B106: ເງິນຝາກປະຈຳ-MRH-MSIG SOKXAY-0381-1276-0101-USD | C106: tYES | D106: 1022.003 | G106: Fixed Accounts-MRH-MSIG SOKXAY-0381-1276-0101-USD | H106: =VLOOKUP(A106,COA!$A:$H,8,FALSE) -> Fixed Accounts - MRH - MSIG SOKXAY - 0381-1276-0101 - USD
A107: 1022.04.01 | B107: ເງິນຝາກປະຈຳ - | C107: tNO | D107: 1022.03 | G107: Fixed Accounts - | H107: =VLOOKUP(A107,COA!$A:$H,8,FALSE) -> Fixed Accounts -
A108: 1023 | B108: ​ເງິນ​ຝາກຄັງເງິນແຫ່ງຊາດ | C108: tNO | D108: 102 | G108: National treasury | H108: =VLOOKUP(A108,COA!$A:$H,8,FALSE) -> National treasury
A109: 1024 | B109: ເງິນ​ຝາກສະ​ຖາບັນ​ການ​ເງິນ​ອື່ນໆ | C109: tNO | D109: 102 | G109: Other financial institutions | H109: =VLOOKUP(A109,COA!$A:$H,8,FALSE) -> Other financial institutions
A110: 1024.01 | B110: ເງິນຝາກທຄບັນຊີກະແສລາຍວັນ | C110: tNO | D110: 1024 | G110: Cash at Banks-Current Accounts | H110: =VLOOKUP(A110,COA!$A:$H,8,FALSE) -> Cash at Banks - Current Accounts
A111: 1024.02 | B111: ເງິນຝາກປະຢັດ | C111: tNO | D111: 1024 | G111: Cash at Banks-Saving Accounts | H111: =VLOOKUP(A111,COA!$A:$H,8,FALSE) -> Cash at Banks - Saving Accounts
A112: 1024.020 | B112: ເງິນຝາກປະຢັດ | C112: tNO | D112: 1024.02 | G112: Cash at Banks-Saving Accounts | H112: =VLOOKUP(A112,COA!$A:$H,8,FALSE) -> Cash at Banks - Saving Accounts
A113: 1024.02.01 | B113: ເງິນຝາກປະຢັດ-SMI-MSIG SOKXAY-01-1121-01-11134-11309 -LAK | C113: tYES | D113: 1024.02 | G113: Saving Accounts-SMI-MSIG SOKXAY-01-1121-01-11134-11309-LAK | H113: =VLOOKUP(A113,COA!$A:$H,8,FALSE) -> Saving Accounts - SMI - MSIG SOKXAY - 01-1121-01-11134-11309 - LAK
A114: 1024.02.02 | B114: ເງິນຝາກປະຢັດ-SMI-SIC-01-1121-01-5585-05268-LAK | C114: tYES | D114: 1024.02 | G114: Saving Accounts-SMI-SIC-01-1121-01-5585-05268-LAK | H114: =VLOOKUP(A114,COA!$A:$H,8,FALSE) -> Saving Accounts - SMI - SIC - 01-1121-01-5585-05268 - LAK
A115: 1024.03 | B115: ເງິນຝາກປະຈຳ | C115: tNO | D115: 1024 | H115: =VLOOKUP(A115,COA!$A:$H,8,FALSE) -> 0
...
